pynotify/__init__.py
pynotify/event.py
pynotify/event_handler.py
pynotify/event_type.py
pynotify/notifier.py
pynotify_mcriley821-0.0.2.dist-info/licenses/UNLICENSE
pynotify_mcriley821-0.0.2.dist-info/METADATA
pynotify_mcriley821-0.0.2.dist-info/WHEEL
pynotify_mcriley821-0.0.2.dist-info/top_level.txt
pynotify_mcriley821-0.0.2.dist-info/RECORD
