Metadata-Version: 2.4
Name: pynotify-mcriley821
Version: 0.0.2
Summary: PyNotify is an async Python interface to the Linux inotify API.
Author: mcriley821
Maintainer: mcriley821
Project-URL: Homepage, https://github.com/mcriley821/pynotify
Project-URL: Documentation, https://mcriley821.github.io/PyNotify/build/html/index.html
Project-URL: Issues, https://github.com/mcriley821/pynotify/issues
Keywords: inotify,async,asyncio,monitor,file monitor
Classifier: Programming Language :: Python :: 3
Classifier: Development Status :: 5 - Production/Stable
Classifier: License :: OSI Approved :: The Unlicense (Unlicense)
Classifier: Operating System :: POSIX :: Linux
Classifier: Topic :: System :: Filesystems
Requires-Python: >=3.10
License-File: UNLICENSE
Dynamic: license-file
